py_terminal_notifier/__init__.py
py_terminal_notifier/exceptions.py
py_terminal_notifier/wrapper.py
py_terminal_notifier-0.1.1.dist-info/WHEEL
py_terminal_notifier-0.1.1.dist-info/METADATA
py_terminal_notifier-0.1.1.dist-info/RECORD
